cloudproof_anonymization-0.1.3.dist-info/METADATA
cloudproof_anonymization-0.1.3.dist-info/WHEEL
cloudproof_anonymization-0.1.3.dist-info/license_files/LICENSE.md
cloudproof_anonymization/__init__.py
cloudproof_anonymization/__init__.pyi
cloudproof_anonymization/py.typed
cloudproof_anonymization/cloudproof_anonymization.pyd
cloudproof_anonymization-0.1.3.dist-info/RECORD
