Metadata-Version: 2.3
Name: cloudproof_anonymization
Version: 0.1.3
Classifier: Programming Language :: Rust
Classifier: Programming Language :: Python :: Implementation :: CPython
Classifier: Programming Language :: Python :: Implementation :: PyPy
Requires-Dist: cffi
License-File: LICENSE.md
Summary: Cosmian Cloudproof Anonymization library
Author: Hugo Rosenkranz-costa<hugo.rosenkranz@cosmian.com>
Author-email: Hugo Rosenkranz-costa<hugo.rosenkranz@cosmian.com>
Requires-Python: >=3.7
Project-URL: Source Code, https://github.com/cosmian/cloudproof_rust/
